clinicaio/__init__.py
clinicaio/hello.py
clinicaio-0.2.0.dist-info/LICENSE
clinicaio-0.2.0.dist-info/METADATA
clinicaio-0.2.0.dist-info/WHEEL
clinicaio-0.2.0.dist-info/RECORD
